pydantic_sqlalchemy_mapper/__init__.py
pydantic_sqlalchemy_mapper/loader.py
pydantic_sqlalchemy_mapper/mapper.py
pydantic_sqlalchemy_mapper-0.1.0.dist-info/LICENSE
pydantic_sqlalchemy_mapper-0.1.0.dist-info/METADATA
pydantic_sqlalchemy_mapper-0.1.0.dist-info/WHEEL
pydantic_sqlalchemy_mapper-0.1.0.dist-info/RECORD
